setup.py
bin/dockdev
dockdev/__init__.py
dockdev/dockdev.py
dockdev.egg-info/PKG-INFO
dockdev.egg-info/SOURCES.txt
dockdev.egg-info/dependency_links.txt
dockdev.egg-info/requires.txt
dockdev.egg-info/top_level.txt