Metadata-Version: 1.1
Name: dockdev
Version: 0.1.4
Summary: A simple development setup tool for docker containerised apps
Home-page: https://github.com/alphagov/dockdev
Author: Ian Maddison
Author-email: ian.maddison@digital.cabinet-office.gov.uk
License: MIT
Keywords: docker container development setup
Platform: UNKNOWN
Classifier: Development Status :: 4 - Beta
Classifier: Topic :: Software Development :: Build Tools
Classifier: License :: OSI Approved :: MIT License
